new_logger/__init__.py
new_logger/_logger.py
new_logger-0.1.0.dist-info/METADATA
new_logger-0.1.0.dist-info/WHEEL
new_logger-0.1.0.dist-info/top_level.txt
new_logger-0.1.0.dist-info/RECORD
