Metadata-Version: 2.4
Name: new_logger
Version: 0.1.0
Summary: Loguru-based logger utilities with file and tracker handlers
Author: anxingle
Project-URL: homepage, https://example.com/new_logger
Keywords: logging,loguru,logger
Requires-Python: >=3.8
Requires-Dist: loguru>=0.7
